chargily_epay_django/__init__.py
chargily_epay_django/admin.py
chargily_epay_django/apps.py
chargily_epay_django/forms.py
chargily_epay_django/models.py
chargily_epay_django/payment_manager.py
chargily_epay_django/tests.py
chargily_epay_django/utils.py
chargily_epay_django/views.py
chargily_epay_django/migrations/__init__.py
chargily_epay_django/static/images/logo-checkout.png
chargily_epay_django/static/images/logo-white-horizon.png
chargily_epay_django/static/images/pay.webp
chargily_epay_django/templates/chargily_epay_django/_base.html
chargily_epay_django/templates/chargily_epay_django/fake-payment-view.html
chargily_epay_django/templates/chargily_epay_django/widgets/fake-payment-form.html
chargily_epay_Django-0.0.2.dist-info/LICENSE
chargily_epay_Django-0.0.2.dist-info/METADATA
chargily_epay_Django-0.0.2.dist-info/WHEEL
chargily_epay_Django-0.0.2.dist-info/top_level.txt
chargily_epay_Django-0.0.2.dist-info/RECORD
